svgpathtools/__init__.py
svgpathtools/bezier.py
svgpathtools/constants.py
svgpathtools/document.py
svgpathtools/misctools.py
svgpathtools/parser.py
svgpathtools/path.py
svgpathtools/paths2svg.py
svgpathtools/polytools.py
svgpathtools/smoothing.py
svgpathtools/svg_io_sax.py
svgpathtools/svg_to_paths.py
svgpathtools_light-1.6.2.dist-info/LICENSE.txt
svgpathtools_light-1.6.2.dist-info/METADATA
svgpathtools_light-1.6.2.dist-info/WHEEL
svgpathtools_light-1.6.2.dist-info/top_level.txt
svgpathtools_light-1.6.2.dist-info/RECORD
